odoo/addons/delivery_free_fee_removal/README.rst
odoo/addons/delivery_free_fee_removal/__init__.py
odoo/addons/delivery_free_fee_removal/__manifest__.py
odoo/addons/delivery_free_fee_removal/i18n/delivery_free_fee_removal.pot
odoo/addons/delivery_free_fee_removal/i18n/es.po
odoo/addons/delivery_free_fee_removal/i18n/it.po
odoo/addons/delivery_free_fee_removal/models/__init__.py
odoo/addons/delivery_free_fee_removal/models/sale_order.py
odoo/addons/delivery_free_fee_removal/models/sale_order_line.py
odoo/addons/delivery_free_fee_removal/readme/CONTRIBUTORS.rst
odoo/addons/delivery_free_fee_removal/readme/CREDITS.rst
odoo/addons/delivery_free_fee_removal/readme/DESCRIPTION.rst
odoo/addons/delivery_free_fee_removal/reports/sale_report_templates.xml
odoo/addons/delivery_free_fee_removal/static/description/icon.png
odoo/addons/delivery_free_fee_removal/static/description/index.html
odoo/addons/delivery_free_fee_removal/tests/__init__.py
odoo/addons/delivery_free_fee_removal/tests/test_delivery_free_fee_removal.py
odoo/addons/delivery_free_fee_removal/views/sale_order_views.xml
odoo14_addon_delivery_free_fee_removal-14.0.1.0.1.dev9.dist-info/METADATA
odoo14_addon_delivery_free_fee_removal-14.0.1.0.1.dev9.dist-info/WHEEL
odoo14_addon_delivery_free_fee_removal-14.0.1.0.1.dev9.dist-info/top_level.txt
odoo14_addon_delivery_free_fee_removal-14.0.1.0.1.dev9.dist-info/RECORD
